[
  {
    "py/object": "model.project.Project",
    "name": "namextE",
    "description": "description8Q@pR",
    "id": null
  },
  {
    "py/object": "model.project.Project",
    "name": "name`  ",
    "description": "description66 6#Yx78Z ~e*3|w I6e",
    "id": null
  },
  {
    "py/object": "model.project.Project",
    "name": "nameLxJ}>",
    "description": "description&a",
    "id": null
  },
  {
    "py/object": "model.project.Project",
    "name": "name2bV*eN",
    "description": "descriptionv.994+k7OCpl+;o",
    "id": null
  },
  {
    "py/object": "model.project.Project",
    "name": "name}#;Z",
    "description": "description'*SR{>",
    "id": null
  }
]